zope.catalog-5.0-py3.11-nspkg.pth
zope/catalog/__init__.py
zope/catalog/apidoc.zcml
zope/catalog/attribute.py
zope/catalog/catalog.py
zope/catalog/classes.zcml
zope/catalog/configure.zcml
zope/catalog/field.py
zope/catalog/interfaces.py
zope/catalog/keyword.py
zope/catalog/subscribers.zcml
zope/catalog/tests.py
zope/catalog/text.py
zope.catalog-5.0.dist-info/LICENSE.txt
zope.catalog-5.0.dist-info/METADATA
zope.catalog-5.0.dist-info/WHEEL
zope.catalog-5.0.dist-info/namespace_packages.txt
zope.catalog-5.0.dist-info/top_level.txt
zope.catalog-5.0.dist-info/RECORD
